{
  "timestamp": "2025-07-24T17:04:00.955264",
  "overall_readiness": 0.2945740045972417,
  "readiness_scores": {
    "Performance": -0.9774951332360708,
    "Statistical_Significance": 0.25,
    "Risk_Management": 0.692596032002626,
    "Stability": 0.5023431288168949,
    "Regime_Robustness": 1.0,
    "Practical_Trading": 0.3
  },
  "test_results": {
    "walk_forward": {
      "fold_performance": [
        {
          "fold": 1,
          "mae": 0.13370759863121923,
          "direction_accuracy": 0.65,
          "mean_return": 0.04009698420654899,
          "std_return": 0.14427017193104555,
          "sharpe_ratio": 0.8055115886919215,
          "max_drawdown": -0.6483628633435145,
          "win_rate": 0.65,
          "profit_factor": 1.8379850734594305,
          "train_start": "2017-09-06 00:00:00",
          "train_end": "2022-01-29 00:00:00",
          "test_start": "2022-01-30 00:00:00",
          "test_end": "2022-07-28 00:00:00",
          "n_test_samples": 20
        },
        {
          "fold": 2,
          "mae": 0.09378546948586246,
          "direction_accuracy": 0.18333333333333332,
          "mean_return": -0.04994588528541238,
          "std_return": 0.09764683528343672,
          "sharpe_ratio": -1.4824386807797272,
          "max_drawdown": -0.9634560191412317,
          "win_rate": 0.18333333333333332,
          "profit_factor": 0.2816341894801856,
          "train_start": "2017-09-06 00:00:00",
          "train_end": "2022-07-28 00:00:00",
          "test_start": "2022-07-29 00:00:00",
          "test_end": "2023-01-24 00:00:00",
          "n_test_samples": 60
        },
        {
          "fold": 3,
          "mae": 0.06220864382540095,
          "direction_accuracy": 0.22580645161290322,
          "mean_return": -0.029582671863603104,
          "std_return": 0.059653466717689445,
          "sharpe_ratio": -1.437255805715716,
          "max_drawdown": -0.9254261516157252,
          "win_rate": 0.22580645161290322,
          "profit_factor": 0.32146179863759655,
          "train_start": "2017-09-06 00:00:00",
          "train_end": "2023-01-24 00:00:00",
          "test_start": "2023-01-25 00:00:00",
          "test_end": "2023-07-23 00:00:00",
          "n_test_samples": 62
        },
        {
          "fold": 4,
          "mae": 0.1609108498120328,
          "direction_accuracy": 0.0,
          "mean_return": -0.14027369024380956,
          "std_return": 0.03403069667219125,
          "sharpe_ratio": -11.946268283252394,
          "max_drawdown": -0.9829565828507691,
          "win_rate": 0.0,
          "profit_factor": 0.0,
          "train_start": "2017-09-06 00:00:00",
          "train_end": "2023-07-23 00:00:00",
          "test_start": "2023-07-24 00:00:00",
          "test_end": "2024-01-19 00:00:00",
          "n_test_samples": 28
        },
        {
          "fold": 5,
          "mae": 0.07743154551406432,
          "direction_accuracy": 0.532258064516129,
          "mean_return": 0.009488332718660316,
          "std_return": 0.0868061099220902,
          "sharpe_ratio": 0.3167920329169086,
          "max_drawdown": -0.8728260406870696,
          "win_rate": 0.532258064516129,
          "profit_factor": 1.2787148542011246,
          "train_start": "2017-09-06 00:00:00",
          "train_end": "2024-01-19 00:00:00",
          "test_start": "2024-01-20 00:00:00",
          "test_end": "2024-07-17 00:00:00",
          "n_test_samples": 62
        },
        {
          "fold": 6,
          "mae": 0.1324877408916057,
          "direction_accuracy": 0.0,
          "mean_return": -0.11472197960395467,
          "std_return": 0.04324848051273289,
          "sharpe_ratio": -7.687858479687979,
          "max_drawdown": -0.9671554602776935,
          "win_rate": 0.0,
          "profit_factor": 0.0,
          "train_start": "2017-09-06 00:00:00",
          "train_end": "2024-07-17 00:00:00",
          "test_start": "2024-07-18 00:00:00",
          "test_end": "2025-01-13 00:00:00",
          "n_test_samples": 29
        },
        {
          "fold": 7,
          "mae": 0.0969652927597338,
          "direction_accuracy": 0.10638297872340426,
          "mean_return": -0.08799037227317501,
          "std_return": 0.06062665188266915,
          "sharpe_ratio": -4.206336861324287,
          "max_drawdown": -0.9886989950647099,
          "win_rate": 0.10638297872340426,
          "profit_factor": 0.012724567325610545,
          "train_start": "2017-09-06 00:00:00",
          "train_end": "2025-01-13 00:00:00",
          "test_start": "2025-01-14 00:00:00",
          "test_end": "2025-07-12 00:00:00",
          "n_test_samples": 47
        }
      ],
      "periods": [],
      "aggregate_metrics": {
        "mean_direction_accuracy": 0.24254011831225283,
        "std_direction_accuracy": 0.2549299535065761,
        "mean_sharpe": -3.6625506413073246,
        "std_sharpe": 4.665875375069419,
        "mean_max_drawdown": -0.9069831589972448,
        "worst_drawdown": -0.6483628633435145,
        "successful_folds": 7,
        "total_folds": 7
      }
    },
    "statistical_significance": {
      "n_samples": 857,
      "direction_accuracy": 0.49008168028004667,
      "p_value_direction": 0.730666832848929,
      "mean_strategy_return": -0.0006552627405488152,
      "mean_random_return": 0.00046982601289094516,
      "p_value_returns": 0.7359583376104821,
      "actual_sharpe": -0.007037112669526535,
      "p_value_permutation": 0.906,
      "is_significant_alpha_05": "False",
      "is_significant_alpha_01": "False"
    },
    "risk_metrics": {
      "total_return": 0.001533797116337867,
      "mean_return": 7.707523197677723e-06,
      "std_return": 5.604033550516584e-05,
      "sharpe_ratio": 0.3916268074104411,
      "sortino_ratio": 0.6981131887962508,
      "max_drawdown": -0.003370407608248815,
      "calmar_ratio": 0.019203609406968726,
      "win_rate": 0.5829145728643216,
      "avg_win": 4.664088653199586e-05,
      "avg_loss": -4.670537013703195e-05,
      "profit_factor": 1.395300849165709,
      "var_95": -9.189459349041374e-05,
      "var_99": -0.00010473799356763772,
      "cvar_95": -0.0001003519665224435,
      "cvar_99": -0.00011131031317629058,
      "risk_adjusted_return": 0.07604710063490441
    },
    "regime_analysis": {
      "regime_performance": {
        "transition": {
          "sample_count": "639",
          "direction_accuracy": 0.5289514866979655,
          "mae": 0.08298043228461983,
          "mean_return": 0.00712588693996719,
          "std_return": 0.1008981039488279,
          "sharpe_ratio": 0.2046874714570052,
          "max_drawdown": -0.9974374364708039,
          "win_rate": 0.5289514866979655
        }
      },
      "regime_stability_score": 1.0,
      "worst_regime": "transition",
      "best_regime": "transition"
    },
    "prediction_stability": {
      "mean_prediction_std": 0.0049638046065523375,
      "max_prediction_std": 0.00726418994366553,
      "mean_direction_agreement": 0.7719298245614035,
      "min_direction_agreement": 0.0,
      "mean_correlation_between_runs": 0.23275643307238625,
      "min_correlation_between_runs": -0.04928204471208396,
      "is_stable": "False"
    },
    "trading_simulation": {
      "initial_capital": 10000,
      "final_capital": 10000,
      "total_return": 0.0,
      "annualized_return": 0.0,
      "sharpe_ratio": 0,
      "max_drawdown": 0.0,
      "n_trades": "0",
      "win_rate": 0.5,
      "avg_trade_return": 0,
      "trade_frequency": 0.0,
      "profitable": false,
      "meets_sharpe_threshold": false,
      "meets_drawdown_threshold": "True"
    },
    "stress_test": {
      "extreme_volatility": {
        "extreme": {
          "direction_accuracy": 0.3103448275862069,
          "mae": 0.13039406967308753,
          "sample_count": 58
        },
        "normal": {
          "direction_accuracy": 0.5065320665083135,
          "mae": 0.0830504813050165,
          "sample_count": 1684
        }
      },
      "black_swan": {
        "n_events": "104",
        "pct_of_data": 0.036645525017618044
      },
      "regime_transitions": {
        "n_transitions": 1892,
        "avg_accuracy_during_transition": 0.0
      },
      "stress_test_score": 0.40507418037757215,
      "passes_stress_test": "False"
    }
  },
  "recommendation": "NOT READY"
}